{
	"archive" : {},
	"artifacts" : 
	[
		{
			"path" : "OrderStatusResolver/libOrderStatusResolver.a"
		}
	],
	"backtrace" : 1,
	"backtraceGraph" : 
	{
		"commands" : 
		[
			"add_library",
			"target_link_libraries",
			"include_directories",
			"target_include_directories"
		],
		"files" : 
		[
			"OrderStatusResolver/CMakeLists.txt",
			"CMakeLists.txt"
		],
		"nodes" : 
		[
			{
				"file" : 0
			},
			{
				"command" : 0,
				"file" : 0,
				"line" : 4,
				"parent" : 0
			},
			{
				"command" : 1,
				"file" : 0,
				"line" : 9,
				"parent" : 0
			},
			{
				"file" : 1
			},
			{
				"command" : 2,
				"file" : 1,
				"line" : 12,
				"parent" : 3
			},
			{
				"command" : 2,
				"file" : 1,
				"line" : 23,
				"parent" : 3
			},
			{
				"command" : 2,
				"file" : 1,
				"line" : 24,
				"parent" : 3
			},
			{
				"command" : 3,
				"file" : 0,
				"line" : 6,
				"parent" : 0
			}
		]
	},
	"compileGroups" : 
	[
		{
			"compileCommandFragments" : 
			[
				{
					"fragment" : "-g -arch arm64 -isysroot /Library/Developer/CommandLineTools/SDKs/MacOSX13.1.sdk -mmacosx-version-min=13.0 -fcolor-diagnostics"
				},
				{
					"fragment" : "-std=gnu++20"
				}
			],
			"defines" : 
			[
				{
					"backtrace" : 2,
					"define" : "FMT_SHARED"
				}
			],
			"includes" : 
			[
				{
					"backtrace" : 4,
					"path" : "/opt/homebrew/Cellar/boost/1.82.0_1/include"
				},
				{
					"backtrace" : 5,
					"path" : "/opt/homebrew/Cellar/spdlog/1.12.0/include"
				},
				{
					"backtrace" : 6,
					"path" : "/opt/homebrew/Cellar/fmt/10.1.1/include"
				},
				{
					"backtrace" : 7,
					"path" : "/Users/james/Documents/sideProjects/LimitOrderBook-MatchingEngine/OrderStatusResolver"
				},
				{
					"backtrace" : 2,
					"path" : "/Users/james/Documents/sideProjects/LimitOrderBook-MatchingEngine/Order"
				},
				{
					"backtrace" : 2,
					"path" : "/Users/james/Documents/sideProjects/LimitOrderBook-MatchingEngine/OrderCore"
				},
				{
					"backtrace" : 2,
					"path" : "/Users/james/Documents/sideProjects/LimitOrderBook-MatchingEngine/CancelOrder"
				},
				{
					"backtrace" : 2,
					"path" : "/Users/james/Documents/sideProjects/LimitOrderBook-MatchingEngine/RejectOrder"
				},
				{
					"backtrace" : 2,
					"path" : "/Users/james/Documents/sideProjects/LimitOrderBook-MatchingEngine/OrderStatus"
				},
				{
					"backtrace" : 2,
					"path" : "/Users/james/Documents/sideProjects/LimitOrderBook-MatchingEngine/RejectionResolver"
				},
				{
					"backtrace" : 2,
					"path" : "/Users/james/Documents/sideProjects/LimitOrderBook-MatchingEngine/OrderBookEntry"
				},
				{
					"backtrace" : 2,
					"path" : "/Users/james/Documents/sideProjects/LimitOrderBook-MatchingEngine/Limit"
				},
				{
					"backtrace" : 2,
					"path" : "/Users/james/Documents/sideProjects/LimitOrderBook-MatchingEngine/OrderBook"
				},
				{
					"backtrace" : 2,
					"path" : "/Users/james/Documents/sideProjects/LimitOrderBook-MatchingEngine/MatchResult"
				},
				{
					"backtrace" : 2,
					"path" : "/Users/james/Documents/sideProjects/LimitOrderBook-MatchingEngine/Security"
				},
				{
					"backtrace" : 2,
					"isSystem" : true,
					"path" : "/opt/homebrew/include"
				}
			],
			"language" : "CXX",
			"languageStandard" : 
			{
				"backtraces" : 
				[
					2
				],
				"standard" : "20"
			},
			"sourceIndexes" : 
			[
				0
			]
		}
	],
	"dependencies" : 
	[
		{
			"id" : "RejectOrder::@6ca2606d47b3056e7301"
		}
	],
	"id" : "OrderStatusResolver::@109da096c6951ae58ff2",
	"name" : "OrderStatusResolver",
	"nameOnDisk" : "libOrderStatusResolver.a",
	"paths" : 
	{
		"build" : "OrderStatusResolver",
		"source" : "OrderStatusResolver"
	},
	"sourceGroups" : 
	[
		{
			"name" : "Source Files",
			"sourceIndexes" : 
			[
				0
			]
		}
	],
	"sources" : 
	[
		{
			"backtrace" : 1,
			"compileGroupIndex" : 0,
			"path" : "OrderStatusResolver/OrderStatusResolver.cpp",
			"sourceGroupIndex" : 0
		}
	],
	"type" : "STATIC_LIBRARY"
}
